income_estimator/__init__.py
income_estimator/income_estimator.py
income_estimator/usd_string_class.py
income_estimator-0.0.1.dist-info/LICENSE
income_estimator-0.0.1.dist-info/METADATA
income_estimator-0.0.1.dist-info/WHEEL
income_estimator-0.0.1.dist-info/top_level.txt
income_estimator-0.0.1.dist-info/RECORD
