Metadata-Version: 2.1
Name: income-estimator
Version: 0.0.1
Summary: Proprietary Python 3.7 package to be used by for Bronsoneering purposes, by permitted personnel.
Author-email: Jacob Bronson <bronsoneering@gmail.com>
License: BRONSONEERING LLC END USER LICENSE AGREEMENT (EULA)
Project-URL: Homepage, https://github.com/helloDestroyerOfWorlds/income_estimator.git
Project-URL: Documentation, https://github.com/helloDestroyerOfWorlds/income_estimator.git
Project-URL: Repository, https://github.com/helloDestroyerOfWorlds/income_estimator.git
Project-URL: Changelog, https://github.com/helloDestroyerOfWorlds/income_estimator.git
Classifier: Intended Audience :: Science/Research
Classifier: License :: Other/Proprietary License
Classifier: Natural Language :: English
Classifier: Programming Language :: Python :: 3
Classifier: Operating System :: Microsoft :: Windows
Classifier: Topic :: Scientific/Engineering
Classifier: Development Status :: 1 - Planning
Requires-Python: >=3.7
License-File: LICENSE
